httptest.py
atlassian_httptest-1.0.0.dist-info/COPYING.txt
atlassian_httptest-1.0.0.dist-info/METADATA
atlassian_httptest-1.0.0.dist-info/WHEEL
atlassian_httptest-1.0.0.dist-info/RECORD
